wiliot_api/__init__.py
wiliot_api/api_client.py
wiliot_api/requirements.txt
wiliot_api/version.py
wiliot_api/edge/__init__.py
wiliot_api/edge/edge.py
wiliot_api/edge/examples/__init__.py
wiliot_api/edge/examples/edge_api.py
wiliot_api/manufacturing/__init__.py
wiliot_api/manufacturing/manufacturing.py
wiliot_api/manufacturing/examples/__init__.py
wiliot_api/manufacturing/examples/mannufacturing_api.py
wiliot_api/platform/__init__.py
wiliot_api/platform/platform.py
wiliot_api/platform/platform_models.py
wiliot_api/platform/examples/__init__.py
wiliot_api/platform/examples/platform_api.py
wiliot_api/security/__init__.py
wiliot_api/security/security.py
wiliot_api/utils/__init__.py
wiliot_api/utils/get_version.py
wiliot_api-4.10.16.dist-info/LICENSE
wiliot_api-4.10.16.dist-info/METADATA
wiliot_api-4.10.16.dist-info/WHEEL
wiliot_api-4.10.16.dist-info/top_level.txt
wiliot_api-4.10.16.dist-info/RECORD
