Metadata-Version: 2.1
Name: wiliot_api
Version: 4.10.16
Summary: A library for interacting with Wiliot's private Cloud API
Home-page: 
Author: Wiliot
Author-email: support@wiliot.com
License: MIT
Project-URL: Bug Tracker, https://WILIOT-ZENDESK-URL
Classifier: Programming Language :: Python :: 3
Classifier: License :: OSI Approved :: MIT License
Classifier: Operating System :: OS Independent
Requires-Python: >=3.6
License-File: LICENSE
Requires-Dist: requests
Requires-Dist: setuptools-scm
Requires-Dist: sgqlc
Requires-Dist: pyjwt (>2)
Requires-Dist: requests (==2.32.4) ; python_version >= "3.10" and python_version < "3.11"
Requires-Dist: setuptools-scm (==8.1.0) ; python_version >= "3.10" and python_version < "3.11"
Requires-Dist: sgqlc (==16.3) ; python_version >= "3.10" and python_version < "3.11"
Requires-Dist: pyjwt (==2.10.1) ; python_version >= "3.10" and python_version < "3.11"
Requires-Dist: cryptography (==36.0.0) ; python_version >= "3.9" and python_version < "3.10"
